<XMBML version="1.0">
    <View id="pkg_items">
        <Attributes>
            <Table key="NPJB00126_122">
                <Pair key="icon"><String>/dev_hdd0/game/HENTOOLBX/USRDIR/IMG/PSPxRU/NPJB00126.PNG</String></Pair>
                <Pair key="title"><String>ソニック･ザ･ヘッジホッグ</String></Pair>
                <Pair key="info"><String>NPJB00126. Игра размер (73.8 MB) и Rap: 2 pkg</String></Pair>
                <Pair key="ingame"><String>disable</String></Pair>
            </Table>
            <Table key="NPJB00590_197">
                <Pair key="icon"><String>/dev_hdd0/game/HENTOOLBX/USRDIR/IMG/PSPxRU/NPJB00590.PNG</String></Pair>
                <Pair key="title"><String>ソウルキャリバーⅡ HD ONLINE</String></Pair>
                <Pair key="info"><String>NPJB00590. Игра размер (3.17 GB) и Rap: 2 pkg</String></Pair>
                <Pair key="ingame"><String>disable</String></Pair>
            </Table>
            <Table key="NPJB00764_216">
                <Pair key="icon"><String>/dev_hdd0/game/HENTOOLBX/USRDIR/IMG/PSPxRU/NPJB00764.PNG</String></Pair>
                <Pair key="title"><String>ソフィーのアトリエ</String></Pair>
                <Pair key="info"><String>NPJB00764. Игра размер (667.44 MB) и Rap: 2 pkg</String></Pair>
                <Pair key="ingame"><String>disable</String></Pair>
            </Table>
        </Attributes>
        <Items>
            <Query
                class="type:x-xmb/folder-pixmap"
                key="NPJB00126_122"
                attr="NPJB00126_122"
                src="xmb://localhost/dev_hdd0/game/HENTOOLBX/USRDIR/TOOLBOX/xmbpd/PSNSTUFFLIST/PSN_jp8_lnk.xml#NPJB00126_122"
            />
            <Query
                class="type:x-xmb/folder-pixmap"
                key="NPJB00590_197"
                attr="NPJB00590_197"
                src="xmb://localhost/dev_hdd0/game/HENTOOLBX/USRDIR/TOOLBOX/xmbpd/PSNSTUFFLIST/PSN_jp8_lnk.xml#NPJB00590_197"
            />
            <Query
                class="type:x-xmb/folder-pixmap"
                key="NPJB00764_216"
                attr="NPJB00764_216"
                src="xmb://localhost/dev_hdd0/game/HENTOOLBX/USRDIR/TOOLBOX/xmbpd/PSNSTUFFLIST/PSN_jp8_lnk.xml#NPJB00764_216"
            />
        </Items>
    </View>

</XMBML>