<XMBML version="1.0"><View id="PS1_HAN_Game_T_items"><Attributes><Table key="PS1_HAN_Game_T_item_1"><Pair key="icon"><String>/dev_hdd0/game/HENTOOLBX/USRDIR/IMAGES/IMAGESPS1GAMES/Tomb Raider</String></Pair><Pair key="title"><String>Tomb Raider (Rus)</String></Pair><Pair key="info"><String>SLUS00152</String></Pair><Pair key="ingame"><String>disable</String></Pair></Table><Table key="PS1_HAN_Game_T_item_2"><Pair key="icon"><String>/dev_hdd0/game/HENTOOLBX/USRDIR/IMAGES/IMAGESPS1GAMES/Tomb Raider 2</String></Pair><Pair key="title"><String>Tomb Raider II (Rus)</String></Pair><Pair key="info"><String>SLUS00437</String></Pair><Pair key="ingame"><String>disable</String></Pair></Table><Table key="PS1_HAN_Game_T_item_3"><Pair key="icon"><String>/dev_hdd0/game/HENTOOLBX/USRDIR/IMAGES/IMAGESPS1GAMES/Tomb Raider 3 Adventure Of Lara Croft</String></Pair><Pair key="title"><String>Tomb Raider III Adventures of Lara Croft (Rus)</String></Pair><Pair key="info"><String>SLUS00649</String></Pair><Pair key="ingame"><String>disable</String></Pair></Table><Table key="PS1_HAN_Game_T_item_4"><Pair key="icon"><String>/dev_hdd0/game/HENTOOLBX/USRDIR/IMAGES/IMAGESPS1GAMES/Tomb Raider IV The Last Revelation</String></Pair><Pair key="title"><String>Tomb Raider IV: The Last Revelation (Rus)</String></Pair><Pair key="info"><String>SLUS00885</String></Pair><Pair key="ingame"><String>disable</String></Pair></Table><Table key="PS1_HAN_Game_T_item_5"><Pair key="icon"><String>/dev_hdd0/game/HENTOOLBX/USRDIR/IMAGES/IMAGESPS1GAMES/Tomb Raider V Chronicles</String></Pair><Pair key="title"><String>Tomb Raider V: Chronicles (Rus)</String></Pair><Pair key="info"><String>SLUS01311</String></Pair><Pair key="ingame"><String>disable</String></Pair></Table><Table key="PS1_HAN_Game_T_item_6"><Pair key="icon"><String>/dev_hdd0/game/HENTOOLBX/USRDIR/IMAGES/IMAGESPS1GAMES/Tekken 2</String></Pair><Pair key="title"><String>Tekken 2 (Eng)</String></Pair><Pair key="info"><String>SCES00255</String></Pair><Pair key="ingame"><String>disable</String></Pair></Table><Table key="PS1_HAN_Game_T_item_7"><Pair key="icon"><String>/dev_hdd0/game/HENTOOLBX/USRDIR/IMAGES/IMAGESPS1GAMES/Tekken 3 Plus</String></Pair><Pair key="title"><String>Tekken 3 Plus (Rus)</String></Pair><Pair key="info"><String>SLUS00402</String></Pair><Pair key="ingame"><String>disable</String></Pair></Table><Table key="PS1_HAN_Game_T_item_8"><Pair key="icon"><String>/dev_hdd0/game/HENTOOLBX/USRDIR/IMAGES/IMAGESPS1GAMES/Twisted Metal</String></Pair><Pair key="title"><String>Twisted Metal (Rus)</String></Pair><Pair key="info"><String>SCUS94304</String></Pair><Pair key="ingame"><String>disable</String></Pair></Table><Table key="PS1_HAN_Game_T_item_13"><Pair key="icon"><String>/dev_hdd0/game/HENTOOLBX/USRDIR/IMAGES/IMAGESPS1GAMES/The Fifth Element</String></Pair><Pair key="title"><String>The Fifth Element (Rus)</String></Pair><Pair key="info"><String>SCES01285</String></Pair><Pair key="ingame"><String>disable</String></Pair></Table></Attributes><Items><Query class="type:x-xmb/folder-pixmap" key="PS1_HAN_Game_T_item_1" attr="PS1_HAN_Game_T_item_1" src="xmb://localhost/dev_hdd0/game/HENTOOLBX/USRDIR/FEATURES/PS1CFWGAMESALPHABET/PS1_CFW_Game_T_link.xml#PS1_HAN_Game_T_item_1_link"/><Query class="type:x-xmb/folder-pixmap" key="PS1_HAN_Game_T_item_2" attr="PS1_HAN_Game_T_item_2" src="xmb://localhost/dev_hdd0/game/HENTOOLBX/USRDIR/FEATURES/PS1CFWGAMESALPHABET/PS1_CFW_Game_T_link.xml#PS1_HAN_Game_T_item_2_link"/><Query class="type:x-xmb/folder-pixmap" key="PS1_HAN_Game_T_item_3" attr="PS1_HAN_Game_T_item_3" src="xmb://localhost/dev_hdd0/game/HENTOOLBX/USRDIR/FEATURES/PS1CFWGAMESALPHABET/PS1_CFW_Game_T_link.xml#PS1_HAN_Game_T_item_3_link"/><Query class="type:x-xmb/folder-pixmap" key="PS1_HAN_Game_T_item_4" attr="PS1_HAN_Game_T_item_4" src="xmb://localhost/dev_hdd0/game/HENTOOLBX/USRDIR/FEATURES/PS1CFWGAMESALPHABET/PS1_CFW_Game_T_link.xml#PS1_HAN_Game_T_item_4_link"/><Query class="type:x-xmb/folder-pixmap" key="PS1_HAN_Game_T_item_5" attr="PS1_HAN_Game_T_item_5" src="xmb://localhost/dev_hdd0/game/HENTOOLBX/USRDIR/FEATURES/PS1CFWGAMESALPHABET/PS1_CFW_Game_T_link.xml#PS1_HAN_Game_T_item_5_link"/><Query class="type:x-xmb/folder-pixmap" key="PS1_HAN_Game_T_item_6" attr="PS1_HAN_Game_T_item_6" src="xmb://localhost/dev_hdd0/game/HENTOOLBX/USRDIR/FEATURES/PS1CFWGAMESALPHABET/PS1_CFW_Game_T_link.xml#PS1_HAN_Game_T_item_6_link"/><Query class="type:x-xmb/folder-pixmap" key="PS1_HAN_Game_T_item_7" attr="PS1_HAN_Game_T_item_7" src="xmb://localhost/dev_hdd0/game/HENTOOLBX/USRDIR/FEATURES/PS1CFWGAMESALPHABET/PS1_CFW_Game_T_link.xml#PS1_HAN_Game_T_item_7_link"/><Query class="type:x-xmb/folder-pixmap" key="PS1_HAN_Game_T_item_8" attr="PS1_HAN_Game_T_item_8" src="xmb://localhost/dev_hdd0/game/HENTOOLBX/USRDIR/FEATURES/PS1CFWGAMESALPHABET/PS1_CFW_Game_T_link.xml#PS1_HAN_Game_T_item_8_link"/><Query class="type:x-xmb/folder-pixmap" key="PS1_HAN_Game_T_item_13" attr="PS1_HAN_Game_T_item_13" src="xmb://localhost/dev_hdd0/game/HENTOOLBX/USRDIR/FEATURES/PS1CFWGAMESALPHABET/PS1_CFW_Game_T_link.xml#PS1_HAN_Game_T_item_13_link"/></Items></View>
﻿</XMBML>