<XMBML version="1.0">
	<View id="dlc">
		<Attributes>
			<Table key="psn_0">
				<Pair key="icon">
					<String>/dev_hdd0/game/HENTOOLBX/USRDIR/icon/tex_xmbpd_psn</String>
				</Pair>
				<Pair key="title">
					<String>0-9</String>
				</Pair>
				<Pair key="info">
					<String>DLC от 0 до 9</String>
				</Pair>
				<Pair key="ingame">
					<String>disable</String>
				</Pair>
				<Pair key="child">
					<String>segment</String>
				</Pair>
			</Table>
			<Table key="psn_1">
				<Pair key="icon">
					<String>/dev_hdd0/game/HENTOOLBX/USRDIR/icon/tex_xmbpd_psn</String>
				</Pair>
				<Pair key="title">
					<String>A-B</String>
				</Pair>
				<Pair key="info">
					<String>DLC от A до B</String>
				</Pair>
				<Pair key="ingame">
					<String>disable</String>
				</Pair>
				<Pair key="child">
					<String>segment</String>
				</Pair>
			</Table>
			<Table key="psn_2">
				<Pair key="icon">
					<String>/dev_hdd0/game/HENTOOLBX/USRDIR/icon/tex_xmbpd_psn</String>
				</Pair>
				<Pair key="title">
					<String>C-D</String>
				</Pair>
				<Pair key="info">
					<String>DLC от C до D</String>
				</Pair>
				<Pair key="ingame">
					<String>disable</String>
				</Pair>
				<Pair key="child">
					<String>segment</String>
				</Pair>
			</Table>
			<Table key="psn_3">
				<Pair key="icon">
					<String>/dev_hdd0/game/HENTOOLBX/USRDIR/icon/tex_xmbpd_psn</String>
				</Pair>
				<Pair key="title">
					<String>E-F</String>
				</Pair>
				<Pair key="info">
					<String>DLC от E до F</String>
				</Pair>
				<Pair key="ingame">
					<String>disable</String>
				</Pair>
				<Pair key="child">
					<String>segment</String>
				</Pair>
			</Table>
			<Table key="psn_4">
				<Pair key="icon">
					<String>/dev_hdd0/game/HENTOOLBX/USRDIR/icon/tex_xmbpd_psn</String>
				</Pair>
				<Pair key="title">
					<String>G-H</String>
				</Pair>
				<Pair key="info">
					<String>DLC от G до H</String>
				</Pair>
				<Pair key="ingame">
					<String>disable</String>
				</Pair>
				<Pair key="child">
					<String>segment</String>
				</Pair>
			</Table>
			<Table key="psn_5">
				<Pair key="icon">
					<String>/dev_hdd0/game/HENTOOLBX/USRDIR/icon/tex_xmbpd_psn</String>
				</Pair>
				<Pair key="title">
					<String>I-J</String>
				</Pair>
				<Pair key="info">
					<String>DLC от I до J</String>
				</Pair>
				<Pair key="ingame">
					<String>disable</String>
				</Pair>
				<Pair key="child">
					<String>segment</String>
				</Pair>
			</Table>
			<Table key="psn_6">
				<Pair key="icon">
					<String>/dev_hdd0/game/HENTOOLBX/USRDIR/icon/tex_xmbpd_psn</String>
				</Pair>
				<Pair key="title">
					<String>K-L</String>
				</Pair>
				<Pair key="info">
					<String>DLC от K до L</String>
				</Pair>
				<Pair key="ingame">
					<String>disable</String>
				</Pair>
				<Pair key="child">
					<String>segment</String>
				</Pair>
			</Table>
			<Table key="psn_7">
				<Pair key="icon">
					<String>/dev_hdd0/game/HENTOOLBX/USRDIR/icon/tex_xmbpd_psn</String>
				</Pair>
				<Pair key="title">
					<String>M-N</String>
				</Pair>
				<Pair key="info">
					<String>DLC от M до N</String>
				</Pair>
				<Pair key="ingame">
					<String>disable</String>
				</Pair>
				<Pair key="child">
					<String>segment</String>
				</Pair>
			</Table>
			<Table key="psn_8">
				<Pair key="icon">
					<String>/dev_hdd0/game/HENTOOLBX/USRDIR/icon/tex_xmbpd_psn</String>
				</Pair>
				<Pair key="title">
					<String>O-P</String>
				</Pair>
				<Pair key="info">
					<String>DLC от O до P</String>
				</Pair>
				<Pair key="ingame">
					<String>disable</String>
				</Pair>
				<Pair key="child">
					<String>segment</String>
				</Pair>
			</Table>
			<Table key="psn_9">
				<Pair key="icon">
					<String>/dev_hdd0/game/HENTOOLBX/USRDIR/icon/tex_xmbpd_psn</String>
				</Pair>
				<Pair key="title">
					<String>Q-R</String>
				</Pair>
				<Pair key="info">
					<String>DLC Q-R</String>
				</Pair>
				<Pair key="ingame">
					<String>disable</String>
				</Pair>
				<Pair key="child">
					<String>segment</String>
				</Pair>
			</Table>
			<Table key="psn_10">
				<Pair key="icon">
					<String>/dev_hdd0/game/HENTOOLBX/USRDIR/icon/tex_xmbpd_psn</String>
				</Pair>
				<Pair key="title">
					<String>S-T</String>
				</Pair>
				<Pair key="info">
					<String>DLC S-T</String>
				</Pair>
				<Pair key="ingame">
					<String>disable</String>
				</Pair>
				<Pair key="child">
					<String>segment</String>
				</Pair>
			</Table>
			<Table key="psn_11">
				<Pair key="icon">
					<String>/dev_hdd0/game/HENTOOLBX/USRDIR/icon/tex_xmbpd_psn</String>
				</Pair>
				<Pair key="title">
					<String>U-V</String>
				</Pair>
				<Pair key="info">
					<String>DLC U-V</String>
				</Pair>
				<Pair key="ingame">
					<String>disable</String>
				</Pair>
				<Pair key="child">
					<String>segment</String>
				</Pair>
			</Table>
			<Table key="psn_12">
				<Pair key="icon">
					<String>/dev_hdd0/game/HENTOOLBX/USRDIR/icon/tex_xmbpd_psn</String>
				</Pair>
				<Pair key="title">
					<String>W-X</String>
				</Pair>
				<Pair key="info">
					<String>DLC W-X</String>
				</Pair>
				<Pair key="ingame">
					<String>disable</String>
				</Pair>
				<Pair key="child">
					<String>segment</String>
				</Pair>
			</Table>
			<Table key="psn_13">
				<Pair key="icon">
					<String>/dev_hdd0/game/HENTOOLBX/USRDIR/icon/tex_xmbpd_psn</String>
				</Pair>
				<Pair key="title">
					<String>Y-Z</String>
				</Pair>
				<Pair key="info">
					<String>DLC Y-Z</String>
				</Pair>
				<Pair key="ingame">
					<String>disable</String>
				</Pair>
				<Pair key="child">
					<String>segment</String>
				</Pair>
			</Table>
		</Attributes>
		<Items>
			<Query class="type:x-xmb/xmlpackagefolder" key="psn_0" attr="psn_0" src="#psn_0_items"/>
			<Query class="type:x-xmb/xmlpackagefolder" key="psn_1" attr="psn_1" src="#psn_1_items"/>
			<Query class="type:x-xmb/xmlpackagefolder" key="psn_2" attr="psn_2" src="#psn_2_items"/>
			<Query class="type:x-xmb/xmlpackagefolder" key="psn_3" attr="psn_3" src="#psn_3_items"/>
			<Query class="type:x-xmb/xmlpackagefolder" key="psn_4" attr="psn_4" src="#psn_4_items"/>
			<Query class="type:x-xmb/xmlpackagefolder" key="psn_5" attr="psn_5" src="#psn_5_items"/>
			<Query class="type:x-xmb/xmlpackagefolder" key="psn_6" attr="psn_6" src="#psn_6_items"/>
			<Query class="type:x-xmb/xmlpackagefolder" key="psn_7" attr="psn_7" src="#psn_7_items"/>
			<Query class="type:x-xmb/xmlpackagefolder" key="psn_8" attr="psn_8" src="#psn_8_items"/>
			<Query class="type:x-xmb/xmlpackagefolder" key="psn_9" attr="psn_9" src="#psn_9_items"/>
			<Query class="type:x-xmb/xmlpackagefolder" key="psn_10" attr="psn_10" src="#psn_10_items"/>
			<Query class="type:x-xmb/xmlpackagefolder" key="psn_11" attr="psn_11" src="#psn_11_items"/>
			<Query class="type:x-xmb/xmlpackagefolder" key="psn_12" attr="psn_12" src="#psn_12_items"/>
			<Query class="type:x-xmb/xmlpackagefolder" key="psn_13" attr="psn_13" src="#psn_13_items"/>
		</Items>
	</View>
	<View id="psn_0_items">
		<Items>
			<Query class="type:x-xmb/folder-pixmap" key="01" src="xmb://localhost/dev_hdd0/game/HENTOOLBX/USRDIR/TOOLBOX/xmbpd/DLC/DLC_0.xml#pkg_items"/>
			<Query class="type:x-xmb/folder-pixmap" key="02" src="xmb://localhost/dev_hdd0/game/HENTOOLBX/USRDIR/TOOLBOX/xmbpd/DLC/DLC_1.xml#pkg_items"/>
			<Query class="type:x-xmb/folder-pixmap" key="03" src="xmb://localhost/dev_hdd0/game/HENTOOLBX/USRDIR/TOOLBOX/xmbpd/DLC/DLC_2.xml#pkg_items"/>
			<Query class="type:x-xmb/folder-pixmap" key="04" src="xmb://localhost/dev_hdd0/game/HENTOOLBX/USRDIR/TOOLBOX/xmbpd/DLC/DLC_3.xml#pkg_items"/>
			<Query class="type:x-xmb/folder-pixmap" key="05" src="xmb://localhost/dev_hdd0/game/HENTOOLBX/USRDIR/TOOLBOX/xmbpd/DLC/DLC_4.xml#pkg_items"/>
			<Query class="type:x-xmb/folder-pixmap" key="06" src="xmb://localhost/dev_hdd0/game/HENTOOLBX/USRDIR/TOOLBOX/xmbpd/DLC/DLC_5.xml#pkg_items"/>
			<Query class="type:x-xmb/folder-pixmap" key="07" src="xmb://localhost/dev_hdd0/game/HENTOOLBX/USRDIR/TOOLBOX/xmbpd/DLC/DLC_6.xml#pkg_items"/>
			<Query class="type:x-xmb/folder-pixmap" key="08" src="xmb://localhost/dev_hdd0/game/HENTOOLBX/USRDIR/TOOLBOX/xmbpd/DLC/DLC_7.xml#pkg_items"/>
			<Query class="type:x-xmb/folder-pixmap" key="09" src="xmb://localhost/dev_hdd0/game/HENTOOLBX/USRDIR/TOOLBOX/xmbpd/DLC/DLC_8.xml#pkg_items"/>
			<Query class="type:x-xmb/folder-pixmap" key="10" src="xmb://localhost/dev_hdd0/game/HENTOOLBX/USRDIR/TOOLBOX/xmbpd/DLC/DLC_9.xml#pkg_items"/>
			<Query class="type:x-xmb/folder-pixmap" key="jp1" src="xmb://localhost/dev_hdd0/game/HENTOOLBX/USRDIR/TOOLBOX/xmbpd/DLC/DLC_jp1.xml#pkg_items"/>
			<Query class="type:x-xmb/folder-pixmap" key="jp2" src="xmb://localhost/dev_hdd0/game/HENTOOLBX/USRDIR/TOOLBOX/xmbpd/DLC/DLC_jp2.xml#pkg_items"/>
			<Query class="type:x-xmb/folder-pixmap" key="jp3" src="xmb://localhost/dev_hdd0/game/HENTOOLBX/USRDIR/TOOLBOX/xmbpd/DLC/DLC_jp3.xml#pkg_items"/>			
		</Items>
	</View>
	<View id="psn_1_items">
		<Items>
			<Query class="type:x-xmb/folder-pixmap" key="11" src="xmb://localhost/dev_hdd0/game/HENTOOLBX/USRDIR/TOOLBOX/xmbpd/DLC/DLC_A.xml#pkg_items"/>
			<Query class="type:x-xmb/folder-pixmap" key="12" src="xmb://localhost/dev_hdd0/game/HENTOOLBX/USRDIR/TOOLBOX/xmbpd/DLC/DLC_B.xml#pkg_items"/>						
		</Items>
	</View>
	<View id="psn_2_items">
		<Items>
			<Query class="type:x-xmb/folder-pixmap" key="13" src="xmb://localhost/dev_hdd0/game/HENTOOLBX/USRDIR/TOOLBOX/xmbpd/DLC/DLC_C.xml#pkg_items"/>
			<Query class="type:x-xmb/folder-pixmap" key="14" src="xmb://localhost/dev_hdd0/game/HENTOOLBX/USRDIR/TOOLBOX/xmbpd/DLC/DLC_D.xml#pkg_items"/>
			<Query class="type:x-xmb/folder-pixmap" key="142" src="xmb://localhost/dev_hdd0/game/HENTOOLBX/USRDIR/TOOLBOX/xmbpd/DLC/DLC_D2.xml#pkg_items"/>						
		</Items>
	</View>
	<View id="psn_3_items">
		<Items>
			<Query class="type:x-xmb/folder-pixmap" key="15" src="xmb://localhost/dev_hdd0/game/HENTOOLBX/USRDIR/TOOLBOX/xmbpd/DLC/DLC_E.xml#pkg_items"/>
			<Query class="type:x-xmb/folder-pixmap" key="16" src="xmb://localhost/dev_hdd0/game/HENTOOLBX/USRDIR/TOOLBOX/xmbpd/DLC/DLC_F.xml#pkg_items"/>						
		</Items>
	</View>
	<View id="psn_4_items">
		<Items>					
			<Query class="type:x-xmb/folder-pixmap" key="17" src="xmb://localhost/dev_hdd0/game/HENTOOLBX/USRDIR/TOOLBOX/xmbpd/DLC/DLC_G.xml#pkg_items"/>			
			<Query class="type:x-xmb/folder-pixmap" key="18" src="xmb://localhost/dev_hdd0/game/HENTOOLBX/USRDIR/TOOLBOX/xmbpd/DLC/DLC_H.xml#pkg_items"/>
			<Query class="type:x-xmb/folder-pixmap" key="182" src="xmb://localhost/dev_hdd0/game/HENTOOLBX/USRDIR/TOOLBOX/xmbpd/DLC/DLC_H2.xml#pkg_items"/>
		</Items>
	</View>
	<View id="psn_5_items">
		<Items>					
			<Query class="type:x-xmb/folder-pixmap" key="19" src="xmb://localhost/dev_hdd0/game/HENTOOLBX/USRDIR/TOOLBOX/xmbpd/DLC/DLC_I.xml#pkg_items"/>
			<Query class="type:x-xmb/folder-pixmap" key="20" src="xmb://localhost/dev_hdd0/game/HENTOOLBX/USRDIR/TOOLBOX/xmbpd/DLC/DLC_J.xml#pkg_items"/>
		</Items>
	</View>
	<View id="psn_6_items">
		<Items>		
			<Query class="type:x-xmb/folder-pixmap" key="21" src="xmb://localhost/dev_hdd0/game/HENTOOLBX/USRDIR/TOOLBOX/xmbpd/DLC/DLC_K.xml#pkg_items"/>
			<Query class="type:x-xmb/folder-pixmap" key="22" src="xmb://localhost/dev_hdd0/game/HENTOOLBX/USRDIR/TOOLBOX/xmbpd/DLC/DLC_L.xml#pkg_items"/>			
		</Items>
	</View>
	<View id="psn_7_items">
		<Items>		
			<Query class="type:x-xmb/folder-pixmap" key="23" src="xmb://localhost/dev_hdd0/game/HENTOOLBX/USRDIR/TOOLBOX/xmbpd/DLC/DLC_M.xml#pkg_items"/>
			<Query class="type:x-xmb/folder-pixmap" key="24" src="xmb://localhost/dev_hdd0/game/HENTOOLBX/USRDIR/TOOLBOX/xmbpd/DLC/DLC_N.xml#pkg_items"/>
		</Items>
	</View>
	<View id="psn_8_items">
		<Items>			
			<Query class="type:x-xmb/folder-pixmap" key="25" src="xmb://localhost/dev_hdd0/game/HENTOOLBX/USRDIR/TOOLBOX/xmbpd/DLC/DLC_O.xml#pkg_items"/>
			<Query class="type:x-xmb/folder-pixmap" key="26" src="xmb://localhost/dev_hdd0/game/HENTOOLBX/USRDIR/TOOLBOX/xmbpd/DLC/DLC_P.xml#pkg_items"/>			
		</Items>
	</View>
	<View id="psn_9_items">
		<Items>			
			<Query class="type:x-xmb/folder-pixmap" key="27" src="xmb://localhost/dev_hdd0/game/HENTOOLBX/USRDIR/TOOLBOX/xmbpd/DLC/DLC_Q.xml#pkg_items"/>
			<Query class="type:x-xmb/folder-pixmap" key="28" src="xmb://localhost/dev_hdd0/game/HENTOOLBX/USRDIR/TOOLBOX/xmbpd/DLC/DLC_R.xml#pkg_items"/>			
		</Items>
	</View>
	<View id="psn_10_items">
		<Items>
			<Query class="type:x-xmb/folder-pixmap" key="29" src="xmb://localhost/dev_hdd0/game/HENTOOLBX/USRDIR/TOOLBOX/xmbpd/DLC/DLC_S.xml#pkg_items"/>
			<Query class="type:x-xmb/folder-pixmap" key="30" src="xmb://localhost/dev_hdd0/game/HENTOOLBX/USRDIR/TOOLBOX/xmbpd/DLC/DLC_T.xml#pkg_items"/>			
		</Items>
	</View>
	<View id="psn_11_items">
		<Items>		
			<Query class="type:x-xmb/folder-pixmap" key="31" src="xmb://localhost/dev_hdd0/game/HENTOOLBX/USRDIR/TOOLBOX/xmbpd/DLC/DLC_U.xml#pkg_items"/>
			<Query class="type:x-xmb/folder-pixmap" key="32" src="xmb://localhost/dev_hdd0/game/HENTOOLBX/USRDIR/TOOLBOX/xmbpd/DLC/DLC_V.xml#pkg_items"/>			
		</Items>
	</View>
	<View id="psn_12_items">
		<Items>					
			<Query class="type:x-xmb/folder-pixmap" key="33" src="xmb://localhost/dev_hdd0/game/HENTOOLBX/USRDIR/TOOLBOX/xmbpd/DLC/DLC_W.xml#pkg_items"/>
			<Query class="type:x-xmb/folder-pixmap" key="34" src="xmb://localhost/dev_hdd0/game/HENTOOLBX/USRDIR/TOOLBOX/xmbpd/DLC/DLC_X.xml#pkg_items"/>			
		</Items>		
	</View>		
	<View id="psn_13_items">
		<Items>								
			<Query class="type:x-xmb/folder-pixmap" key="35" src="xmb://localhost/dev_hdd0/game/HENTOOLBX/USRDIR/TOOLBOX/xmbpd/DLC/DLC_Y.xml#pkg_items"/>
			<Query class="type:x-xmb/folder-pixmap" key="36" src="xmb://localhost/dev_hdd0/game/HENTOOLBX/USRDIR/TOOLBOX/xmbpd/DLC/DLC_Z.xml#pkg_items"/>
		</Items>		
	</View>		
</XMBML>